setup.cfg
setup.py
pysutils/__init__.py
pysutils/config.py
pysutils/datastructures.py
pysutils/datetime.py
pysutils/decorators.py
pysutils/error_handling.py
pysutils/filesystem.py
pysutils/functional.py
pysutils/helpers.py
pysutils/importing.py
pysutils/numbers.py
pysutils/sentinels.py
pysutils/spreadsheets.py
pysutils/strings.py
pysutils.egg-info/PKG-INFO
pysutils.egg-info/SOURCES.txt
pysutils.egg-info/dependency_links.txt
pysutils.egg-info/top_level.txt