Metadata-Version: 1.0
Name: pysutils
Version: 0.2
Summary: A collection of python utility functions and classes.
Home-page: http://pypi.python.org/pypi/pysutils/
Author: Randy Syring
Author-email: rsyring@gmail.com
License: BSD
Platform: UNKNOWN
Classifier: Development Status :: 4 - Beta
Classifier: Intended Audience :: Developers
Classifier: License :: OSI Approved :: BSD License
